service_identity/__init__.py
service_identity/_common.py
service_identity/_compat.py
service_identity/cryptography.py
service_identity/exceptions.py
service_identity/pyopenssl.py
service_identity-17.0.0.dist-info/DESCRIPTION.rst
service_identity-17.0.0.dist-info/METADATA
service_identity-17.0.0.dist-info/RECORD
service_identity-17.0.0.dist-info/WHEEL
service_identity-17.0.0.dist-info/metadata.json
service_identity-17.0.0.dist-info/top_level.txt
